{
    "Model_Type": "Series2Vec",
    "Norm": false,
    "Training_mode": "Pre_Training",
    "batch_size": 64,
    "console": false,
    "data_dir": "/Users/jessekroll/Desktop/Bachelor Thesis 24/Repos for TSCAR models/Series2Vec/Dataset/UCR",
    "dataset": "UCR",
    "dim_ff": 256,
    "dropout": 0.01,
    "emb_size": 16,
    "epochs": 100,
    "gpu": 0,
    "key_metric": "accuracy",
    "layers": 4,
    "lr": 0.001,
    "num_heads": 8,
    "output_dir": "./outputs/Pre_Training/UCR/2025-05-15_10-06",
    "pred_dir": "./outputs/Pre_Training/UCR/2025-05-15_10-06/predictions",
    "print_interval": 10,
    "problem": "Adiac",
    "rep_size": 320,
    "save_dir": "./outputs/Pre_Training/UCR/2025-05-15_10-06/checkpoints",
    "seed": 18,
    "tensorboard_dir": "./outputs/Pre_Training/UCR/2025-05-15_10-06/tb_summaries",
    "val_interval": 2,
    "val_ratio": 0.2
}